ccaf_housekeeping_python_lib/__init__.py
ccaf_housekeeping_python_lib/drop_table_with_associated_resources.py
ccaf_housekeeping_python_lib/py.typed
ccaf_housekeeping_python_lib-0.2.0.0.dist-info/METADATA
ccaf_housekeeping_python_lib-0.2.0.0.dist-info/WHEEL
ccaf_housekeeping_python_lib-0.2.0.0.dist-info/licenses/LICENSE.md
ccaf_housekeeping_python_lib-0.2.0.0.dist-info/RECORD
