Metadata-Version: 2.4
Name: ccaf-housekeeping-python_lib
Version: 0.2.0.0
Summary: CCAF Housekeeping Python Library
Author-email: "Jeffrey Jonathan Jennings (J3)" <j3@thej3.com>
License-File: LICENSE.md
Requires-Python: >=3.11.9
Requires-Dist: cc-clients-python-lib>=0.13.0.0
Requires-Dist: pytest>=8.3.4
